libscol/__init__.py
libscol-0.9.1.dist-info/WHEEL
libscol-0.9.1.dist-info/METADATA
libscol-0.9.1.dist-info/RECORD
