Metadata-Version: 2.1
Name: libscol
Version: 0.9.1
Summary: LIBrary to convert integers into Spreadsheet COLumn names, and vice versa
Home-page: https://pypi.org/project/libscol
License: UNKNOWN
Author: Carlo Alessandro Verre
Author-email: carlo.alessandro.verre@gmail.com
Requires-Python: >=3.7
Classifier: Programming Language :: Python :: 3
Classifier: Programming Language :: Python :: 3.7
Classifier: Development Status :: 4 - Beta
Classifier: Environment :: Console
Classifier: Intended Audience :: Developers
Classifier: License :: OSI Approved :: GNU General Public License v3 or later (GPLv3+)
Classifier: Operating System :: POSIX :: Linux
